fastapi_device_id/__init__.py
fastapi_device_id/middleware.py
fastapi_device_id/strategies.py
fastapi_device_id-0.1.0.dist-info/METADATA
fastapi_device_id-0.1.0.dist-info/WHEEL
fastapi_device_id-0.1.0.dist-info/licenses/LICENSE
fastapi_device_id-0.1.0.dist-info/RECORD
