Metadata-Version: 2.4
Name: fastapi-device-id
Version: 0.1.0
Summary: Drop-in device tracking for FastAPI - persistent IDs without user accounts
Project-URL: Homepage, https://github.com/ideatives/fastapi-device-id
Project-URL: Repository, https://github.com/ideatives/fastapi-device-id
Project-URL: Documentation, https://github.com/ideatives/fastapi-device-id
Project-URL: Bug Tracker, https://github.com/ideatives/fastapi-device-id/issues
Author-email: Ideatives <info@ideatives.com>
Maintainer-email: Ideatives <info@ideatives.com>
License-Expression: MIT
License-File: LICENSE
Keywords: a-b-testing,analytics,anonymous-tracking,cookie,device-tracking,fastapi,middleware,rate-limiting,session-management,starlette,uuid,web-analytics
Classifier: Development Status :: 4 - Beta
Classifier: Environment :: Web Environment
Classifier: Framework :: AsyncIO
Classifier: Framework :: FastAPI
Classifier: Intended Audience :: Developers
Classifier: License :: OSI Approved :: MIT License
Classifier: Operating System :: OS Independent
Classifier: Programming Language :: Python :: 3
Classifier: Programming Language :: Python :: 3.8
Classifier: Programming Language :: Python :: 3.9
Classifier: Programming Language :: Python :: 3.10
Classifier: Programming Language :: Python :: 3.11
Classifier: Programming Language :: Python :: 3.12
Classifier: Programming Language :: Python :: 3.13
Classifier: Topic :: Internet :: WWW/HTTP :: Dynamic Content
Classifier: Topic :: Internet :: WWW/HTTP :: HTTP Servers
Classifier: Topic :: Internet :: WWW/HTTP :: Session
Classifier: Topic :: Internet :: WWW/HTTP :: WSGI :: Middleware
Classifier: Topic :: Software Development :: Libraries :: Python Modules
Classifier: Topic :: System :: Monitoring
Classifier: Typing :: Typed
Requires-Python: >=3.8
Requires-Dist: fastapi>=0.68.0
Requires-Dist: starlette>=0.14.0
Provides-Extra: crypto
Requires-Dist: cryptography>=3.4.0; extra == 'crypto'
Provides-Extra: dev
Requires-Dist: black>=22.0.0; extra == 'dev'
Requires-Dist: bumpversion>=0.6.0; extra == 'dev'
Requires-Dist: httpx>=0.23.0; extra == 'dev'
Requires-Dist: mypy>=1.0.0; extra == 'dev'
Requires-Dist: pre-commit>=2.20.0; extra == 'dev'
Requires-Dist: pytest-asyncio>=0.21.0; extra == 'dev'
Requires-Dist: pytest>=7.0.0; extra == 'dev'
Requires-Dist: ruff>=0.1.0; extra == 'dev'
Provides-Extra: docs
Requires-Dist: mkdocs-material>=8.0.0; extra == 'docs'
Requires-Dist: mkdocs>=1.4.0; extra == 'docs'
Requires-Dist: mkdocstrings[python]>=0.19.0; extra == 'docs'
Provides-Extra: jwt
Requires-Dist: pyjwt>=2.4.0; extra == 'jwt'
